novaml/__init__.py
novaml/models/__init__.py
novaml/models/linear_regression.py
novaml/utils/__init__.py
novaml/utils/feature_scaling.py
novaml-1.0.0.dist-info/METADATA
novaml-1.0.0.dist-info/WHEEL
novaml-1.0.0.dist-info/licenses/LICENSE
novaml-1.0.0.dist-info/RECORD
