Metadata-Version: 2.1
Name: novaml
Version: 1.0.0
Summary: Build machine learning applications with NovaML; The NEW machine learning library!
Project-URL: Homepage, https://github.com/maelghrib/novaml
Project-URL: Issues, https://github.com/maelghrib/novaml/issues
Author-email: "Mustafa A. Elghrib" <maelghrib@gmail.com>
License-File: LICENSE
Classifier: License :: OSI Approved :: MIT License
Classifier: Operating System :: OS Independent
Classifier: Programming Language :: Python :: 3
Requires-Python: >=3.11
